pybest-2.1.0.dist-info/WHEEL
pybest-2.1.0.dist-info/METADATA
pybest-2.1.0.dist-info/top_level.txt
pybest-2.1.0.dist-info/RECORD
pybest-2.1.0.dist-info/licenses/COPYING
pybest-2.1.0.data/data/requirements.txt
pybest-2.1.0.data/scripts/pybest-entanglement.py
pybest-2.1.0.data/scripts/pybest-benchmark-cd-eri.py
pybest-2.1.0.data/scripts/pybest-convert.py
pybest.libs/libgfortran-040039e1.so.5.0.0
pybest.libs/libint2-787a1edb.so.2.9.0
pybest.libs/libchol-020aa2b2.so
pybest.libs/libgomp-a34b3233.so.1.0.0
pybest.libs/libquadmath-96973f99.so.0.0.0
pybest.libs/libopenblas-67c19dcf.so.0.3
pybest/periodic.py
pybest/conftest.py
pybest/exceptions.py
pybest/context.py
pybest/auxmat.py
pybest/_pytesttester.py
pybest/constants.py
pybest/_numpy.py
pybest/__init__.py
pybest/cache.py
pybest/log.py
pybest/units.py
pybest/file_manager.py
pybest/helperclass.py
pybest/featuredlists.py
pybest/scf/scf_plain.py
pybest/scf/hamiltonian.py
pybest/scf/observable.py
pybest/scf/scf_ediis.py
pybest/scf/scf_diis.py
pybest/scf/__init__.py
pybest/scf/convergence.py
pybest/scf/scf_ediis2.py
pybest/scf/scf_cdiis.py
pybest/scf/utils.py
pybest/scf/guess.py
pybest/scf/tests/common.py
pybest/scf/tests/__init__.py
pybest/scf/tests/test_scf.py
pybest/ea_eom/xea_pccd.py
pybest/ea_eom/dea_pccd2.py
pybest/ea_eom/dea_base.py
pybest/ea_eom/sea_pccd3.py
pybest/ea_eom/dea_pccd4.py
pybest/ea_eom/sea_rccd1.py
pybest/ea_eom/__init__.py
pybest/ea_eom/sea_pccd1_sf.py
pybest/ea_eom/xea_base.py
pybest/ea_eom/xea_rcc.py
pybest/ea_eom/sea_base.py
pybest/ea_eom/dea_pccd0.py
pybest/ea_eom/sea_pccd1.py
pybest/ea_eom/sea_rccsd1.py
pybest/ea_eom/tests/conftest.py
pybest/ea_eom/tests/common.py
pybest/ea_eom/tests/test_sea_base.py
pybest/ea_eom/tests/__init__.py
pybest/ea_eom/tests/test_dea_base.py
pybest/ea_eom/tests/test_xea_pccd.py
pybest/ea_eom/tests/test_sea_pccd.py
pybest/ea_eom/tests/test_sea_rcc.py
pybest/ea_eom/tests/test_dea_pccd.py
pybest/ea_eom/tests/test_xea_base.py
pybest/tests/test_exceptions.py
pybest/tests/common.py
pybest/tests/test_filemanager.py
pybest/tests/test_log.py
pybest/tests/__init__.py
