Metadata-Version: 2.4
Name: pybest
Version: 2.1.0
Summary: PyBEST: Pythonic Black-box Electronic Structure Tool.
Home-page: http://www.fizyka.umk.pl/~pybest
Author: Somayeh Ahmadkhani <so.ahmadkhani@gmail.com>, Katharina Boguslawski <k.boguslawski@fizyka.umk.pl>, Iulia Brumboiu <iubr@umk.pl>, Marta Gałyńska <marta.galynska@gmail.com>, Dariusz Kędziera <teodar@chem.umk.pl>, Maximilian Kriebel <maximilian.kriebel@web.de>, Paweł Tecmer <ptecmer@fizyka.umk.pl>, Piotr Żuchowski <pzuch@fizyka.umk.pl>, Saman Behjou <s.behjoo@gmail.com>, Filip Brzęk <filip.brzek@gmail.com>, Rahul Chakraborty <rahuldev.chakraborty91@gmail.com>, Kacper Cieślak <kacperfonex@gm
Classifier: Development Status :: 4 - Beta
Classifier: Environment :: Console
Classifier: Intended Audience :: Science/Research
Classifier: License :: OSI Approved :: GNU General Public License (GPL)
Classifier: Operating System :: MacOS
Classifier: Operating System :: POSIX :: Linux
Classifier: Programming Language :: Python :: 3
Classifier: Programming Language :: C++
Classifier: Topic :: Scientific/Engineering :: Physics
Classifier: Topic :: Scientific/Engineering :: Chemistry
Requires-Python: >=3.9,<4.0
License-File: COPYING
Requires-Dist: h5py<4.0.0,>=3.11.0
Requires-Dist: numpy<3.0.0,>=2.0.0
Requires-Dist: pylatexenc<3.0.0,>=2.8.0
Requires-Dist: pytest<8.0.0,>=6.2.4
Requires-Dist: pytest-durations~=1.2.0
Requires-Dist: pytest-xdist[psutil]~=2.5.0
Requires-Dist: scipy<2.0.0,>=1.13.0
Provides-Extra: scripts
Requires-Dist: matplotlib; extra == "scripts"
Provides-Extra: einsum
Requires-Dist: opt_einsum~=3.3.0; extra == "einsum"
Provides-Extra: all
Requires-Dist: matplotlib; extra == "all"
Requires-Dist: opt_einsum~=3.3.0; extra == "all"
Dynamic: author
Dynamic: classifier
Dynamic: description
Dynamic: description-content-type
Dynamic: home-page
Dynamic: license-file
Dynamic: provides-extra
Dynamic: requires-dist
Dynamic: requires-python
Dynamic: summary
